rapidus/__init__.py
rapidus/client.py
rapidus-0.1.0.dist-info/LICENSE.txt
rapidus-0.1.0.dist-info/METADATA
rapidus-0.1.0.dist-info/WHEEL
rapidus-0.1.0.dist-info/top_level.txt
rapidus-0.1.0.dist-info/RECORD
