Metadata-Version: 2.2
Name: rapidus
Version: 0.1.0
Summary: A short description of your package
Home-page: https://github.com/EvgeniiGerasin/rapidus-api-test-framework
Author: Evgenii Gerasin
Author-email: e.d.gerasin@yandex.ru
Project-URL: Bug Reports, https://github.com/EvgeniiGerasin/rapidus-api-test-framework/issues
Project-URL: Source, https://github.com/EvgeniiGerasin/rapidus-api-test-framework
Classifier: Programming Language :: Python :: 3
Classifier: License :: OSI Approved :: MIT License
Classifier: Operating System :: OS Independent
Requires-Python: >=3.11
License-File: LICENSE.txt
Requires-Dist: allure-pytest>=2.13.5
Requires-Dist: requests>=2.32.3
Requires-Dist: pytest>=8.3.4
Dynamic: author
Dynamic: author-email
Dynamic: classifier
Dynamic: description
Dynamic: description-content-type
Dynamic: home-page
Dynamic: project-url
Dynamic: requires-dist
Dynamic: requires-python
Dynamic: summary
